maui/__init__.py
maui/acoustic_indices/.ipynb_checkpoints/Untitled-checkpoint.ipynb
maui/acoustic_indices/__init__.py
maui/acoustic_indices/acoustic_indices.py
maui/data/audio_samples/leec_data_test_sample.zip
maui/data/letterhead.png
maui/data/letterhead_cover.png
maui/data/logo/Black logo - no background.svg
maui/data/logo/Color logo with background.svg
maui/data/logo/White logo - no background.svg
maui/data/logo/color_logo_no_background.png
maui/data/logo/color_logo_no_background.svg
maui/data/logo/favicon.ico
maui/data/logo/main_logo.svg
maui/eda/__init__.py
maui/eda/eda.py
maui/files_metadata/__init__.py
maui/files_metadata/files_formats.yaml
maui/files_metadata/files_metadata.py
maui/io/__init__.py
maui/io/io.py
maui/samples/__init__.py
maui/samples/audio_samples.py
maui/utils/__init__.py
maui/utils/utils.py
maui/visualizations/__init__.py
maui/visualizations/visualizations.py
maui_software-0.2.6.dist-info/LICENSE
maui_software-0.2.6.dist-info/METADATA
maui_software-0.2.6.dist-info/WHEEL
maui_software-0.2.6.dist-info/RECORD
