Metadata-Version: 2.3
Name: maui-software
Version: 0.2.6
Summary: Eco-acoustics data visualization and analysis
Author: Caio Ferreira Bernardo
Author-email: caio.bernardo@usp.br
Requires-Python: >=3.9,<3.13
Classifier: Programming Language :: Python :: 3
Classifier: Programming Language :: Python :: 3.9
Classifier: Programming Language :: Python :: 3.10
Classifier: Programming Language :: Python :: 3.11
Classifier: Programming Language :: Python :: 3.12
Requires-Dist: audioread (>=3.0.0,<4.0.0)
Requires-Dist: fastparquet (>=2024.5.0,<2025.0.0)
Requires-Dist: fpdf (>=1.7.2,<2.0.0)
Requires-Dist: gdown (>=5.2.0,<6.0.0)
Requires-Dist: kaleido (==0.2.1)
Requires-Dist: matplotlib (>=3.8.3,<4.0.0)
Requires-Dist: numpy (>=1.21)
Requires-Dist: objgraph (>=3.6.1,<4.0.0)
Requires-Dist: pandas (>=1.5)
Requires-Dist: plotly (>=5.16.1,<6.0.0)
Requires-Dist: pyarrow (>=17.0.0,<18.0.0)
Requires-Dist: pydub (>=0.25.1,<0.26.0)
Requires-Dist: pyyaml (>=6.0.1,<7.0.0)
Requires-Dist: scikit-maad (>=1.3.0,<2.0.0)
Requires-Dist: tqdm (>=4.66.1,<5.0.0)
